dataclass_toolkit/__init__.py
dataclass_toolkit/as_list.py
dataclass_toolkit-0.1.3.dist-info/licenses/LICENSE
tests/test_as_list.py
dataclass_toolkit-0.1.3.dist-info/METADATA
dataclass_toolkit-0.1.3.dist-info/WHEEL
dataclass_toolkit-0.1.3.dist-info/top_level.txt
dataclass_toolkit-0.1.3.dist-info/RECORD
