Metadata-Version: 2.4
Name: dataclass_toolkit
Version: 0.1.3
Summary: Utilities for working with Python dataclasses: serialize and deserialize to list with nested support.
Author-email: Klishin Oleg <klishinoleg@gmail.com>
License: MIT
Project-URL: Homepage, https://github.com/klishinoleg/dataclass_toolkit
Project-URL: Repository, https://github.com/klishinoleg/dataclass_toolkit
Requires-Python: >=3.11
License-File: LICENSE
Dynamic: license-file
